frame_semantic_transformer/FrameSemanticTransformer.py
frame_semantic_transformer/__init__.py
frame_semantic_transformer/constants.py
frame_semantic_transformer/data/LoaderDataCache.py
frame_semantic_transformer/data/TaskSampleDataset.py
frame_semantic_transformer/data/augmentations/DataAugmentation.py
frame_semantic_transformer/data/augmentations/DoubleQuotesAugmentation.py
frame_semantic_transformer/data/augmentations/KeyboardAugmentation.py
frame_semantic_transformer/data/augmentations/LowercaseAugmentation.py
frame_semantic_transformer/data/augmentations/RemoveEndPunctuationAugmentation.py
frame_semantic_transformer/data/augmentations/SimpleMisspellingAugmentation.py
frame_semantic_transformer/data/augmentations/StripPunctuationAugmentation.py
frame_semantic_transformer/data/augmentations/SynonymAugmentation.py
frame_semantic_transformer/data/augmentations/UppercaseAugmentation.py
frame_semantic_transformer/data/augmentations/__init__.py
frame_semantic_transformer/data/augmentations/chain_augmentations.py
frame_semantic_transformer/data/augmentations/modification_helpers/__init__.py
frame_semantic_transformer/data/augmentations/modification_helpers/get_sample_text.py
frame_semantic_transformer/data/augmentations/modification_helpers/modify_text_without_changing_length.py
frame_semantic_transformer/data/augmentations/modification_helpers/splice_text.py
frame_semantic_transformer/data/data_utils.py
frame_semantic_transformer/data/frame_types.py
frame_semantic_transformer/data/loaders/framenet17/Framenet17InferenceLoader.py
frame_semantic_transformer/data/loaders/framenet17/Framenet17TrainingLoader.py
frame_semantic_transformer/data/loaders/framenet17/__init__.py
frame_semantic_transformer/data/loaders/framenet17/ensure_framenet_downloaded.py
frame_semantic_transformer/data/loaders/framenet17/ensure_wordnet_downloaded.py
frame_semantic_transformer/data/loaders/framenet17/sesame_data_splits.py
frame_semantic_transformer/data/loaders/loader.py
frame_semantic_transformer-0.10.0.dist-info/LICENSE
frame_semantic_transformer-0.10.0.dist-info/METADATA
frame_semantic_transformer-0.10.0.dist-info/WHEEL
frame_semantic_transformer-0.10.0.dist-info/RECORD
