Metadata-Version: 2.1
Name: frame-semantic-transformer
Version: 0.10.0
Summary: Frame Semantic Parser based on T5 and FrameNet
Home-page: https://github.com/chanind/frame-semantic-transformer
License: MIT
Author: David Chanin
Author-email: chanindav@gmail.com
Requires-Python: >=3.8,<4.0
Classifier: License :: OSI Approved :: MIT License
Classifier: Programming Language :: Python :: 3
Classifier: Programming Language :: Python :: 3.8
Classifier: Programming Language :: Python :: 3.9
Classifier: Programming Language :: Python :: 3.10
Classifier: Programming Language :: Python :: 3.11
Requires-Dist: nlpaug (>=1.1.11,<2.0.0)
Requires-Dist: nltk (>=3.7,<4.0)
Requires-Dist: protobuf (>=3.20.1,<4.0.0)
Requires-Dist: pytorch-lightning (>=1.6.2,<2.0.0)
Requires-Dist: sentencepiece (>=0.1.97,<0.2.0)
Requires-Dist: tqdm (>=4.64.0,<5.0.0)
Requires-Dist: transformers (>=4.18.0,<5.0.0)
Project-URL: Repository, https://github.com/chanind/frame-semantic-transformer
